matrixctl/__init__.py
matrixctl/__main__.py
matrixctl/argparse_action.py
matrixctl/command.py
matrixctl/errors.py
matrixctl/package_version.py
matrixctl/parse.py
matrixctl/password_helpers.py
matrixctl/print_helpers.py
matrixctl/py.typed
matrixctl/sanitizers.py
matrixctl/structures.py
matrixctl/terminal.py
matrixctl/typehints.py
matrixctl/commands/__init__.py
matrixctl/commands/adduser/__init__.py
matrixctl/commands/adduser/addon.py
matrixctl/commands/adduser/parser.py
matrixctl/commands/check/__init__.py
matrixctl/commands/check/addon.py
matrixctl/commands/check/parser.py
matrixctl/commands/delete_local_media/__init__.py
matrixctl/commands/delete_local_media/addon.py
matrixctl/commands/delete_local_media/parser.py
matrixctl/commands/delroom/__init__.py
matrixctl/commands/delroom/addon.py
matrixctl/commands/delroom/parser.py
matrixctl/commands/deluser/__init__.py
matrixctl/commands/deluser/addon.py
matrixctl/commands/deluser/parser.py
matrixctl/commands/deploy/__init__.py
matrixctl/commands/deploy/addon.py
matrixctl/commands/deploy/parser.py
matrixctl/commands/download/__init__.py
matrixctl/commands/download/addon.py
matrixctl/commands/download/parser.py
matrixctl/commands/get_event/__init__.py
matrixctl/commands/get_event/addon.py
matrixctl/commands/get_event/parser.py
matrixctl/commands/get_event_context/__init__.py
matrixctl/commands/get_event_context/addon.py
matrixctl/commands/get_event_context/parser.py
matrixctl/commands/get_events/__init__.py
matrixctl/commands/get_events/addon.py
matrixctl/commands/get_events/parser.py
matrixctl/commands/is_admin/__init__.py
matrixctl/commands/is_admin/addon.py
matrixctl/commands/is_admin/parser.py
matrixctl/commands/joinroom/__init__.py
matrixctl/commands/joinroom/addon.py
matrixctl/commands/joinroom/parser.py
matrixctl/commands/largest_rooms/__init__.py
matrixctl/commands/largest_rooms/addon.py
matrixctl/commands/largest_rooms/parser.py
matrixctl/commands/largest_rooms/to_table.py
matrixctl-0.15.2.dist-info/METADATA
matrixctl-0.15.2.dist-info/WHEEL
matrixctl-0.15.2.dist-info/entry_points.txt
matrixctl-0.15.2.dist-info/licenses/LICENSE.txt
matrixctl-0.15.2.dist-info/RECORD
