Metadata-Version: 2.4
Name: matrixctl
Version: 0.15.2
Summary: Control, manage, provision and deploy matrix homeservers.
Project-URL: Homepage, https://michaelsasser.github.io/matrixctl/index.html
Project-URL: Documentation, https://michaelsasser.github.io/matrixctl/index.html
Project-URL: Repository, https://github.com/MichaelSasser/matrixctl
Project-URL: Issues, https://github.com/MichaelSasser/matrixctl/issues
Project-URL: Changelog, https://github.com/MichaelSasser/matrixctl/blob/main/CHANGELOG.md
Author-email: Michael Sasser <Michael@MichaelSasser.org>
Maintainer-email: Michael Sasser <Michael@MichaelSasser.org>
License-File: LICENSE.txt
Keywords: Docker,Matrix,Synapse
Classifier: Development Status :: 3 - Alpha
Classifier: Environment :: Console
Classifier: Intended Audience :: Customer Service
Classifier: Intended Audience :: Developers
Classifier: Intended Audience :: Other Audience
Classifier: Intended Audience :: System Administrators
Classifier: License :: OSI Approved :: GNU General Public License v3 or later (GPLv3+)
Classifier: Natural Language :: English
Classifier: Operating System :: POSIX
Classifier: Operating System :: POSIX :: Linux
Classifier: Operating System :: Unix
Classifier: Programming Language :: Python :: 3 :: Only
Classifier: Programming Language :: Python :: 3.10
Classifier: Programming Language :: Python :: 3.11
Classifier: Programming Language :: Python :: 3.12
Classifier: Programming Language :: Python :: 3.13
Classifier: Topic :: Utilities
Classifier: Typing :: Typed
Requires-Python: <4.0,>=3.10
Requires-Dist: ansible-runner<3.0.0,>=2.4.0
Requires-Dist: attrs>=23.2.0
Requires-Dist: coloredlogs<16.0.0,>=15.0.1
Requires-Dist: dateparser>=1.2.0
Requires-Dist: gitpython<4.0.0,>=3.1.43
Requires-Dist: httpx[http2]>=0.27.2
Requires-Dist: jinja2<4.0.0,>=3.1.4
Requires-Dist: packaging>=24.2
Requires-Dist: paramiko<4.0.0,>=3.4.0
Requires-Dist: psycopg<4.0.0,>=3.1.19
Requires-Dist: python-dateutil>=2.9.0.post0
Requires-Dist: rich<14.1.0,>=14.0.0
Requires-Dist: ruamel-yaml>=0.18.6
Requires-Dist: sshtunnel<0.5.0,>=0.4.0
Requires-Dist: typing-extensions>=4.12.2
Requires-Dist: xdg-base-dirs<7.0.0,>=6.0.0
Provides-Extra: docs
Requires-Dist: exceptiongroup>=1.2.2; (python_version < '3.11') and extra == 'docs'
Requires-Dist: myst-parser>=4.0.0; extra == 'docs'
Requires-Dist: numpydoc>=1.5.0; extra == 'docs'
Requires-Dist: sphinx-autodoc-typehints<3.3,>=3; extra == 'docs'
Requires-Dist: sphinx-rtd-theme<4.0,>=3.0; extra == 'docs'
Requires-Dist: sphinx<9.0.0,>=8.0.0; extra == 'docs'
Requires-Dist: sphinxcontrib-programoutput>=0.17; extra == 'docs'
Requires-Dist: tomli>=2.0.2; (python_version < '3.11') and extra == 'docs'
